canty/__init__.py
canty/__main__.py
canty/py.typed
canty-0.1.0.dist-info/METADATA
canty-0.1.0.dist-info/WHEEL
canty-0.1.0.dist-info/licenses/LICENSE
canty-0.1.0.dist-info/RECORD
